fastapi_filters/__init__.py
fastapi_filters/config.py
fastapi_filters/configs.py
fastapi_filters/docs.py
fastapi_filters/ext/__init__.py
fastapi_filters/ext/sqlalchemy.py
fastapi_filters/ext/tortoise.py
fastapi_filters/fields.py
fastapi_filters/filter_set.py
fastapi_filters/filters.py
fastapi_filters/op.py
fastapi_filters/operators.py
fastapi_filters/py.typed
fastapi_filters/schemas.py
fastapi_filters/sorters.py
fastapi_filters/types.py
fastapi_filters/utils.py
fastapi_filters_wbarnha-0.2.10.dist-info/LICENSE
fastapi_filters_wbarnha-0.2.10.dist-info/METADATA
fastapi_filters_wbarnha-0.2.10.dist-info/WHEEL
fastapi_filters_wbarnha-0.2.10.dist-info/RECORD
