Metadata-Version: 2.1
Name: fastapi-filters-wbarnha
Version: 0.2.10
Summary: fastapi-filters, just a fork to experiment with
Home-page: https://github.com/uriyyo/fastapi-filters
License: MIT
Author: Yurii Karabas
Author-email: 1998uriyyo@gmail.com
Requires-Python: >=3.8,<4.0
Classifier: License :: OSI Approved :: MIT License
Classifier: Operating System :: OS Independent
Classifier: Programming Language :: Python
Classifier: Programming Language :: Python :: 3
Classifier: Programming Language :: Python :: 3.8
Classifier: Programming Language :: Python :: 3.9
Classifier: Programming Language :: Python :: 3.10
Classifier: Programming Language :: Python :: 3.11
Classifier: Programming Language :: Python :: 3.12
Classifier: Programming Language :: Python :: 3 :: Only
Provides-Extra: all
Provides-Extra: sqlalchemy
Provides-Extra: tortoise-orm
Requires-Dist: fastapi (>=0.100.0)
Requires-Dist: pydantic (>=2.0.0,<3.0.0)
Requires-Dist: sqlalchemy (>=2.0.0,<3.0.0) ; extra == "sqlalchemy" or extra == "all"
Requires-Dist: tortoise-orm (>=0.20.0,<0.21.0) ; extra == "tortoise-orm" or extra == "all"
Requires-Dist: typing-extensions (>=4.4.0,<5.0.0)
Project-URL: Repository, https://github.com/uriyyo/fastapi-filters
